CHANGES.txt
COPYRIGHT.txt
LICENSE.txt
README.txt
buildout.cfg
setup.py
src/zc/__init__.py
src/zc.iso8601.egg-info/PKG-INFO
src/zc.iso8601.egg-info/SOURCES.txt
src/zc.iso8601.egg-info/dependency_links.txt
src/zc.iso8601.egg-info/namespace_packages.txt
src/zc.iso8601.egg-info/not-zip-safe
src/zc.iso8601.egg-info/requires.txt
src/zc.iso8601.egg-info/top_level.txt
src/zc/iso8601/README.txt
src/zc/iso8601/__init__.py
src/zc/iso8601/parse.py
src/zc/iso8601/tests.py