Metadata-Version: 1.0
Name: zc.iso8601
Version: 0.2.0
Summary: ISO 8601 utility functions
Home-page: http://pypi.python.org/pypi/zc.iso8601/
Author: Fred Drake
Author-email: fdrake@gmail.com
License: ZPL 2.1
Platform: any
Classifier: License :: OSI Approved :: Zope Public License
Classifier: Programming Language :: Python
